gevent_memcached_server-0.2.0.dist-info/DESCRIPTION.rst
gevent_memcached_server-0.2.0.dist-info/entry_points.txt
gevent_memcached_server-0.2.0.dist-info/METADATA
gevent_memcached_server-0.2.0.dist-info/metadata.json
gevent_memcached_server-0.2.0.dist-info/RECORD
gevent_memcached_server-0.2.0.dist-info/top_level.txt
gevent_memcached_server-0.2.0.dist-info/WHEEL
gmcbs/__init__.py
gmcbs/const.py
gmcbs/protocol.py
gmcbs/server.py
