Metadata-Version: 2.0
Name: gevent-memcached-server
Version: 0.2.0
Summary: gevent based memcached binary protocol server
Home-page: https://github.com/jvtm/gevent-memcached-server
Author: Jyrki Muukkonen
Author-email: jvtm@kruu.org
License: MIT
Keywords: gevent memcached memcache binary protocol server
Platform: UNKNOWN
Classifier: Development Status :: 3 - Alpha
Classifier: License :: OSI Approved :: MIT License
Classifier: Intended Audience :: Developers
Classifier: Programming Language :: Python :: 2
Classifier: Programming Language :: Python :: 2.7
Requires-Dist: gevent
